Q9/TFF.v
// Positive Edge Triggered Active Low Asynchronous Reset FLip FLip
`timescale 1ns / 1ps

// Changing the definition of the reset to test the state 11 in q9b
module TFF(input T, input Clk, input Reset, output reg Q, output reg Not_Q);
    
    always @(posedge Clk or negedge Reset) 
    begin
        if(!Reset)
        begin
            Q <= 1'b1;
            Not_Q <= 1'b0;
        end
        else
        begin
            if(T)
                Q = ~Q;
            Not_Q = ~Q;
        end
    end

endmodule

Q9/qb.v
`timescale 1ns / 1ps

`include "TFF.v"

// COnsidering A and B as the outputs
module Cir9b (input Clk, input Rst, output Aout, output Bout);

    wire Not_Aout, Not_Bout;
    wire Ain, Bin;

    assign Ain = Aout | Bout;
    assign Bin = Not_Aout | Bout;

    TFF A(.T(Ain), .Clk(Clk), .Reset(Rst), .Q(Aout), .Not_Q(Not_Aout));
    TFF B(.T(Bin), .Clk(Clk), .Reset(Rst), .Q(Bout), .Not_Q(Not_Bout));
    
endmodule

Q9/qb_Testbench.v
`timescale 1ns / 1ps

module qb_Testbench;

    reg Clk, Clr;
    wire A, B;

    Cir9b uut(.Clk(Clk), .Rst(Clr), .Aout(A), .Bout(B));

    initial
    begin
        Clk = 0;
        Clr = 0;
        #1
        Clr = 1;
        forever #5 Clk = ~Clk;
    end

    initial
    begin
        $dumpfile("qb.vcd");
        $dumpvars(0, qb_Testbench);
        
        #100 $finish;

    end

endmodule

Q9/qb.vcd
$date
	Sat Oct  5 13:59:06 2024
$end
$version
	Icarus Verilog
$end
$timescale
	1ps
$end
$scope module qb_Testbench $end
$var wire 1 ! B $end
$var wire 1 " A $end
$var reg 1 # Clk $end
$var reg 1 $ Clr $end
$scope module uut $end
$var wire 1 % Ain $end
$var wire 1 & Bin $end
$var wire 1 # Clk $end
$var wire 1 $ Rst $end
$var wire 1 ' Not_Bout $end
$var wire 1 ( Not_Aout $end
$var wire 1 ! Bout $end
$var wire 1 " Aout $end
$scope module A $end
$var wire 1 # Clk $end
$var wire 1 $ Reset $end
$var wire 1 % T $end
$var reg 1 ( Not_Q $end
$var reg 1 " Q $end
$upscope $end
$scope module B $end
$var wire 1 # Clk $end
$var wire 1 $ Reset $end
$var wire 1 & T $end
$var reg 1 ' Not_Q $end
$var reg 1 ! Q $end
$upscope $end
$upscope $end
$upscope $end
$enddefinitions $end
$comment Show the parameter values. $end
$dumpall
$end
#0
$dumpvars
0(
0'
1&
1%
0$
0#
1"
1!
$end
#1000
1$
#6000
0%
1'
0!
1(
0"
1#
#11000
0#
#16000
1%
0'
1!
1#
#21000
0#
#26000
0&
1'
0!
0(
1"
1#
#31000
0#
#36000
1&
0%
1(
0"
1#
#41000
0#
#46000
1%
0'
1!
1#
#51000
0#
#56000
0&
0(
1"
1'
0!
1#
#61000
0#
#66000
1&
0%
1(
0"
1#
#71000
0#
#76000
1%
0'
1!
1#
#81000
0#
#86000
0&
1'
0!
0(
1"
1#
#91000
0#
#96000
1&
0%
1(
0"
1#
