Q11/q11.v
`timescale 1ns / 1ps

module FSMSequenceDetector (input X, input Clk, input Clr, output reg Y);

    reg [2 : 0] CurrFFs;
    reg [2 : 0] NextFFs;

    always @(posedge Clk or posedge Clr)
    begin
        if(Clr)
        begin
            CurrFFs = 0;
            Y = 0;
        end
        else
        begin
           CurrFFs = NextFFs;
            Y = ((CurrFFs == 3'b111) ? 1 : 0); 
        end
    end

    always @(*)
    begin

        case (CurrFFs)
            3'b000 : NextFFs = (X ? 3'b010 : 3'b001);
            3'b001 : NextFFs = (X ? 3'b011 : 3'b001);
            3'b010 : NextFFs = (X ? 3'b010 : 3'b100);
            3'b011 : NextFFs = (X ? 3'b011 : 3'b101);
            3'b100 : NextFFs = (X ? 3'b110 : 3'b100);
            3'b101 : NextFFs = (X ? 3'b111 : 3'b101);
            3'b110 : NextFFs = (X ? 3'b110 : 3'b111);
            3'b111 : NextFFs = (X ? 3'b111 : 3'b111);
            // default: NextFFs = (X ? 3'b010 : 3'b001);
        endcase

    end
    
endmodule

Q11/q11_Testbench.v
`timescale 1ns / 1ps

module q11_Testbench;

    reg Clk, Clr, x;
    wire y;

    FSMSequenceDetector uut(.Clk(Clk), .Clr(Clr), .X(x), .Y(y));

    initial
    begin
        Clk = 0;
        Clr = 1;
        #1
        Clr = 0;
        forever #5 Clk = ~Clk; // 6, 16, 26, ...
    end

    initial
    begin
        $dumpfile("q11.vcd");
        $dumpvars(1, uut);
        
        x = 0;

        for(integer i = 0; i < 4; i++)
        begin
            x = ~x;
            #20;
        end

        Clr = 1;
        #10;
        Clr = 0;
        x = 1;

        for(integer i = 0; i < 4; i++)
        begin
            x = ~x;
            #20;
        end

        $finish;

    end

endmodule

Q11/q11.vcd
$date
	Sat Oct  5 21:10:56 2024
$end
$version
	Icarus Verilog
$end
$timescale
	1ps
$end
$scope module q11_Testbench $end
$scope module uut $end
$var wire 1 ! Clk $end
$var wire 1 " Clr $end
$var wire 1 # X $end
$var reg 3 $ CurrFFs [2:0] $end
$var reg 3 % NextFFs [2:0] $end
$var reg 1 & Y $end
$upscope $end
$upscope $end
$enddefinitions $end
$comment Show the parameter values. $end
$dumpall
$end
#0
$dumpvars
0&
b10 %
b0 $
1#
1"
0!
$end
#1000
0"
#6000
b10 $
1!
#11000
0!
#16000
1!
#20000
b100 %
0#
#21000
0!
#26000
b100 $
1!
#31000
0!
#36000
1!
#40000
b110 %
1#
#41000
0!
#46000
b110 $
1!
#51000
0!
#56000
1!
#60000
b111 %
0#
#61000
0!
#66000
1&
b111 $
1!
#71000
0!
#76000
1!
#80000
b1 %
0&
b0 $
1"
#81000
0!
#86000
1!
#90000
0#
0"
#91000
0!
#96000
b1 $
1!
#101000
0!
#106000
1!
#110000
b11 %
1#
#111000
0!
#116000
b11 $
1!
#121000
0!
#126000
1!
#130000
b101 %
0#
#131000
0!
#136000
b101 $
1!
#141000
0!
#146000
1!
#150000
b111 %
1#
#151000
0!
#156000
1&
b111 $
1!
