Q5/DFF.v
// Positive Edge Triggered Active Low Asynchronous Reset FLip FLip
`timescale 1ns / 1ps

module DFF(input D, input Clk, input Reset, output reg Q, output reg Not_Q);
    
    always @(posedge Clk or negedge Reset) 
    begin
        if(!Reset)
        begin
            Q <= 1'b0;
            Not_Q <= 1'b1;
        end
        else
        begin
            Q <= D;
            Not_Q <= ~D;
        end
    end

endmodule

Q7/MUX2x1.v
`timescale 1ns / 1ps

module Mux2x1(in1, in2, s0, y);

    input in1, in2, s0;
    output y;
    wire Nots0, p, q;

    not N1(Nots0, s0);
    and A1(p, in1, Nots0);
    and A2(q, in2, s0);
    or O1(y, p, q);

endmodule

Q7/MUX4x1.v
`timescale 1ns / 1ps

`include "MUX2x1.v"

module Mux4x1(in, s, y);

    input [3:0]in;
    input [1:0]s;
    output y;
    wire mux1, mux2;

    Mux2x1 Mux1(in[0], in[1], s[0], mux1);
    Mux2x1 Mux2(in[2], in[3], s[0], mux2);
    Mux2x1 Mux3(mux1, mux2, s[1], y);

endmodule

Q7/ShiftRegNBit.v
`timescale 1ns / 1ps

`include "MUX4x1.v"
`include "DFF.v"

module UniShiftRegNBit #(parameter N = 3)(input [1:0]S, input [N - 1:0]Load, input SRin, input SLin, input Clr, input Clk, output wire [N - 1:0]Out);

/*
    {S1, S0} = 00 = Hold
    {S1, S0} = 01 = Right Shift
    {S1, S0} = 10 = Left Shift
    {S1, S0} = 11 = Parallel Load
    Load = Parallel Load Bits, Load[0] = I0, ...
    Out = Parallel Out, Out[0] = A0, ...
    SRin = Right Shift Input, MSB
    SLin = LEft Shift Input, LSB
    Clr = Reset
*/

    wire [N - 1:0]Not_Out;
    wire [N - 1:0]MUX_To_DFF;

    genvar i;

    generate
        for(i = N - 1; i >= 0; i = i - 1)
        begin : MUX_Loop
            if(i == N - 1)
                Mux4x1 mux({Load[i], Out[i - 1], SRin, Out[i]}, S, MUX_To_DFF[i]);    
            else if(i == 0)
                Mux4x1 mux({Load[i], SLin, Out[i + 1], Out[i]}, S, MUX_To_DFF[i]);
            else
                Mux4x1 mux({Load[i], Out[i - 1], Out[i + 1], Out[i]}, S, MUX_To_DFF[i]);
        end
    endgenerate

    generate
        for(i = N - 1; i >= 0; i = i - 1)
        begin : DFF_Loop
            DFF dff(MUX_To_DFF[i], Clk, Clr, Out[i], Not_Out[i]);
        end
    endgenerate

endmodule

Q7/ADDER1BIT.v
`timescale 1ns / 1ps

module FullAdder1Bit (a, b, c, Sum, Carry);

    input a, b, c;
    output Sum, Carry;
    wire andAB, andBC, andAC;

    xor X1(Sum, a, b, c);

    and A5(andAB, a, b);
    and A6(andBC, c, b);
    and A7(andAC, a, c);

    or O2(Carry, andAB, andAC, andBC);
    
endmodule

Q7/SerialAdder3Bit.v
`timescale 1ns / 1ps

`include "ShiftRegNBit.v"
`include "ADDER1BIT.v"

module SerialAdder3Bit(input Clr, input Clk, input SRInB, input [1:0]S, output wire [2:0]OA);

    wire OutD, InD, SRInA, SLInA, SLInB, ClkD, Not_D;
    wire [2:0]OB;

    assign SLInA = 0;
    assign SLInB = 0;

    assign ClkD = Clk & (~S[1]) & S[0];

    FullAdder1Bit Adder(OA[0], OB[0], OutD, SRInA, InD);
    UniShiftRegNBit #(.N(3)) RegA (.S(S), .Load(OA), .SRin(SRInA), .SLin(SLInA), .Clk(Clk), .Clr(Clr), .Out(OA));
    UniShiftRegNBit #(.N(3)) RegB (.S(S), .Load(OB), .SRin(SRInB), .SLin(SLInB), .Clk(Clk), .Clr(Clr), .Out(OB));
    DFF Dff(InD, ClkD, Clr, OutD, Not_D);

endmodule

Q7/SerialAdder3Bit_Testbench.v
`timescale 1ns / 1ps

module SerialAdder_Testbench;

    reg [1:0]S;
    reg SRinB, Clr, Clk;
    wire [2:0]OutA;

    SerialAdder3Bit uut(.SRInB(SRinB), .Clr(Clr), .Clk(Clk), .OA(OutA), .S(S));

    initial
    begin
        Clk = 0;
        #1
        forever #5 Clk = ~Clk;
    end

    initial
    begin
        $dumpfile("SerialAdder3Bit.vcd");
        $dumpvars(1, uut);    

        // Initialize inputs
        S = 2'b01; // Only want Hold or Right shift, 0 or 1
        SRinB = 1;
        Clr = 0; // Active Low, Reset all the elements
        Clk = 1;
        
        // // Reset
        // #10;
        // S = 1; // Try to shift right
        // #20;
        // Clr = 1;
        // #20; // Should Shift now
        
        // // Hold
        // S = 2'b00;
        // #10; // Output shouldn't change
        
        // // Right Shift
        // S = 2'b01;
        // SRinB = 1;
        // #40; // Right Shift Multiple Times
        
        // // Right Shift
        // S = 2'b01;
        // SRinB = 1;
        // #40; // Right Shift Multiple Times
        
        // Test Case 010 + 011 = 101
        // #10 Clr = 1; SRinB = 0;
        // #10 SRinB = 1;
        // #10 SRinB = 0;
        // #10 SRinB = 1;
        // #20 SRinB = 0;
        // #40;

        // Test Case 110 + 011 = 1001
        #10 Clr = 1; SRinB = 0;
        #10 SRinB = 1;
        #40 SRinB = 0;
        #40;

        $finish;
    end

endmodule

Q7/SerialAdder3Bit.vcd
$date
	Fri Oct  4 19:40:37 2024
$end
$version
	Icarus Verilog
$end
$timescale
	1ps
$end
$scope module SerialAdder_Testbench $end
$scope module uut $end
$var wire 1 ! Clk $end
$var wire 1 " ClkD $end
$var wire 1 # Clr $end
$var wire 2 $ S [1:0] $end
$var wire 1 % SLInA $end
$var wire 1 & SLInB $end
$var wire 1 ' SRInB $end
$var wire 1 ( SRInA $end
$var wire 1 ) OutD $end
$var wire 3 * OB [2:0] $end
$var wire 3 + OA [2:0] $end
$var wire 1 , Not_D $end
$var wire 1 - InD $end
$upscope $end
$upscope $end
$enddefinitions $end
$comment Show the parameter values. $end
$dumpall
$end
#0
$dumpvars
0-
1,
b0 +
b0 *
0)
0(
1'
0&
0%
b1 $
0#
1"
1!
$end
#6000
0"
0!
#10000
0'
1#
#11000
1"
1!
#16000
0"
0!
#20000
1'
#21000
b100 *
1"
1!
#26000
0"
0!
#31000
b110 *
1"
1!
#36000
0"
0!
#41000
1(
b111 *
1"
1!
#46000
0"
0!
#51000
b100 +
1"
1!
#56000
0"
0!
#60000
0'
#61000
b110 +
b11 *
1"
1!
#66000
0"
0!
#71000
1-
0(
b1 *
b111 +
1"
1!
#76000
0"
0!
#81000
0,
1)
b11 +
b0 *
1"
1!
#86000
0"
0!
#91000
b1 +
1"
1!
