Q5/DFF.v
// Positive Edge Triggered Active Low Asynchronous Reset FLip FLip
`timescale 1ns / 1ps

module DFF(input D, input Clk, input Reset, output reg Q, output reg Not_Q);
    
    always @(posedge Clk or negedge Reset) 
    begin
        if(!Reset)
        begin
            Q <= 1'b0;
            Not_Q <= 1'b1;
        end
        else
        begin
            Q <= D;
            Not_Q <= ~D;
        end
    end

endmodule

Q5/DFF_Testbench.v
// Positive Edge Triggered Active Low Asynchronous Reset FLip FLip
`timescale 1ns / 1ps

module DFF_Testbench;

    reg clk;
    reg rst;
    reg D;
    wire Q, Q_Not;
    
    DFF uut (.Clk(clk), .Reset(rst), .D(D), .Q(Q), .Not_Q(Q_Not));

    initial begin
        $dumpfile("DFF.vcd");
        $dumpvars(1, uut);
        
        clk = 1;
        rst = 0;
        D = 0;
        
        #160 $finish;
    end

    initial
    begin
        #1;
        forever #5 clk = ~clk;
    end

    always #20 D = ~D;
    always #80 rst = ~rst;

endmodule

Q5/DFF.vcd
$date
	Fri Oct  4 06:53:41 2024
$end
$version
	Icarus Verilog
$end
$timescale
	1ps
$end
$scope module DFF_Testbench $end
$scope module uut $end
$var wire 1 ! Clk $end
$var wire 1 " D $end
$var wire 1 # Reset $end
$var reg 1 $ Not_Q $end
$var reg 1 % Q $end
$upscope $end
$upscope $end
$enddefinitions $end
$comment Show the parameter values. $end
$dumpall
$end
#0
$dumpvars
0%
1$
0#
0"
1!
$end
#6000
0!
#11000
1!
#16000
0!
#20000
1"
#21000
1!
#26000
0!
#31000
1!
#36000
0!
#40000
0"
#41000
1!
#46000
0!
#51000
1!
#56000
0!
#60000
1"
#61000
1!
#66000
0!
#71000
1!
#76000
0!
#80000
0"
1#
#81000
1!
#86000
0!
#91000
1!
#96000
0!
#100000
1"
#101000
0$
1%
1!
#106000
0!
#111000
1!
#116000
0!
#120000
0"
#121000
1$
0%
1!
#126000
0!
#131000
1!
#136000
0!
#140000
1"
#141000
0$
1%
1!
#146000
0!
#151000
1!
#156000
0!
#160000
1$
0%
0"
0#
