Q5/TFF.v
// Positive Edge Triggered Active Low Asynchronous Reset FLip FLip
`timescale 1ns / 1ps

module TFF(input T, input Clk, input Reset, output reg Q, output reg Not_Q);
    
    always @(posedge Clk or negedge Reset) 
    begin
        if(!Reset)
        begin
            Q <= 1'b0;
            Not_Q <= 1'b1;
        end
        else
        begin
            if(T)
                Q = ~Q;
            Not_Q = ~Q;
        end
    end

endmodule

Q5/TFF_Testbench.v
// Positive Edge Triggered Active Low Asynchronous Reset FLip FLip
`timescale 1ns / 1ps

module TFF_Testbench;

    reg clk;
    reg rst;
    reg T;
    wire Q, Q_Not;
    
    TFF uut (.Clk(clk), .Reset(rst), .T(T), .Q(Q), .Not_Q(Q_Not));

    initial
    begin
        $dumpfile("TFF.vcd");
        $dumpvars(1, uut);
        
        clk = 1;
        rst = 0;
        T = 0;
        
        #160 $finish;
    end

    initial
    begin
        #1;
        forever #5 clk = ~clk;
    end

    always #20 T = ~T;
    always #80 rst = ~rst;

endmodule

Q5/TFF.vcd
$date
	Thu Oct  3 22:11:02 2024
$end
$version
	Icarus Verilog
$end
$timescale
	1ps
$end
$scope module TFF_Testbench $end
$scope module uut $end
$var wire 1 ! Clk $end
$var wire 1 " Reset $end
$var wire 1 # T $end
$var reg 1 $ Not_Q $end
$var reg 1 % Q $end
$upscope $end
$upscope $end
$enddefinitions $end
$comment Show the parameter values. $end
$dumpall
$end
#0
$dumpvars
0%
1$
0#
0"
1!
$end
#5000
0!
#10000
1!
#15000
0!
#20000
1!
1#
#25000
0!
#30000
1!
#35000
0!
#40000
1!
0#
#45000
0!
#50000
1!
#55000
0!
#60000
1!
1#
#65000
0!
#70000
1!
#75000
0!
#80000
1!
0#
1"
#85000
0!
#90000
1!
#95000
0!
#100000
0$
1%
1!
1#
#105000
0!
#110000
1$
0%
1!
#115000
0!
#120000
1!
0#
#125000
0!
#130000
1!
#135000
0!
#140000
0$
1%
1!
1#
#145000
0!
#150000
1$
0%
1!
#155000
0!
#160000
1!
0#
0"
