Q7/MUX2x1.v
`timescale 1ns / 1ps

module Mux2x1(in1, in2, s0, y);

    input in1, in2, s0;
    output y;
    wire Nots0, p, q;

    not N1(Nots0, s0);
    and A1(p, in1, Nots0);
    and A2(q, in2, s0);
    or O1(y, p, q);

endmodule

Q3/MUX/MUX2x1_Testbench.v
`timescale 1ns / 1ps

module Mux2x1_Test;

    reg a, b, en;
    wire y;

    Mux2x1 uut(.in1(a), .in2(b), .s0(en), .y(y));

    initial begin
    
        $dumpfile("MUX2x1.vcd");
        $dumpvars(1, uut);

        a = 1'b0;
        b = 1'b0;
        en = 1'b0;

        #40 $finish;

    end

    always #5 a = ~a;
    always #10 b = ~b;
    always #20 en = ~en;

endmodule

Q3/MUX/MUX2x1.vcd
$date
	Tue Oct  1 18:52:56 2024
$end
$version
	Icarus Verilog
$end
$timescale
	1ps
$end
$scope module Mux2x1_Test $end
$scope module uut $end
$var wire 1 ! Nots0 $end
$var wire 1 " in1 $end
$var wire 1 # in2 $end
$var wire 1 $ p $end
$var wire 1 % q $end
$var wire 1 & s0 $end
$var wire 1 ' y $end
$upscope $end
$upscope $end
$enddefinitions $end
$comment Show the parameter values. $end
$dumpall
$end
#0
$dumpvars
0'
0&
0%
0$
0#
0"
1!
$end
#5000
1'
1$
1"
#10000
0'
0$
0"
1#
#15000
1'
1$
1"
#20000
0'
0$
0!
0"
0#
1&
#25000
1"
#30000
1'
1%
0"
1#
#35000
1"
#40000
0'
1!
0%
0"
0#
0&
