Q7/MUX2x1.v
`timescale 1ns / 1ps

module Mux2x1(in1, in2, s0, y);

    input in1, in2, s0;
    output y;
    wire Nots0, p, q;

    not N1(Nots0, s0);
    and A1(p, in1, Nots0);
    and A2(q, in2, s0);
    or O1(y, p, q);

endmodule

Q3/MUX/MUX4x1.v
`timescale 1ns / 1ps

module Mux4x1(in, s, y);

    input [3:0]in;
    input [1:0]s;
    output y;
    wire mux1, mux2;

    Mux2x1 Mux1(in[0], in[1], s[0], mux1);
    Mux2x1 Mux2(in[2], in[3], s[0], mux2);
    Mux2x1 Mux3(mux1, mux2, s[1], y);

endmodule

Q3/MUX/MUX4x1_Testbench.v
`timescale 1ns / 1ps

module Mux4x1_Test;

    reg [3:0]in;
    reg [1:0]en;
    wire y;

    Mux4x1 uut(.in(in), .s(en), .y(y));

    initial begin
    
        $dumpfile("MUX4x1.vcd");
        $dumpvars(1, uut);

        for(integer i = 0; i < 64; i++)
        begin
            {en[1], en[0], in[3], in[2], in[1], in[0]} = i; 
            #5;
        end

        $finish;

    end

    // always #5 in[0] = ~in[0];
    // always #10 in[1] = ~in[1];
    // always #20 in[2] = ~in[2];
    // always #40 in[3] = ~in[3];
    // always #80 en[0] = ~en[0];
    // always #160 en[1] = ~en[1];

endmodule

Q3/MUX/MUX4x1.vcd
$date
	Wed Oct  2 15:00:33 2024
$end
$version
	Icarus Verilog
$end
$timescale
	1ps
$end
$scope module Mux4x1_Test $end
$scope module uut $end
$var wire 4 ! in [3:0] $end
$var wire 2 " s [1:0] $end
$var wire 1 # y $end
$var wire 1 $ mux2 $end
$var wire 1 % mux1 $end
$upscope $end
$upscope $end
$enddefinitions $end
$comment Show the parameter values. $end
$dumpall
$end
#0
$dumpvars
0%
0$
0#
b0 "
b0 !
$end
#5000
1#
1%
b1 !
#10000
0#
0%
b10 !
#15000
1#
1%
b11 !
#20000
0#
1$
0%
b100 !
#25000
1#
1%
b101 !
#30000
0#
0%
b110 !
#35000
1#
1%
b111 !
#40000
0#
0$
0%
b1000 !
#45000
1#
1%
b1001 !
#50000
0#
0%
b1010 !
#55000
1#
1%
b1011 !
#60000
0#
1$
0%
b1100 !
#65000
1#
1%
b1101 !
#70000
0#
0%
b1110 !
#75000
1#
1%
b1111 !
#80000
0#
0$
0%
b1 "
b0 !
#85000
b1 !
#90000
1#
1%
b10 !
#95000
b11 !
#100000
0#
0%
b100 !
#105000
b101 !
#110000
1#
1%
b110 !
#115000
b111 !
#120000
0#
1$
0%
b1000 !
#125000
b1001 !
#130000
1#
1%
b1010 !
#135000
b1011 !
#140000
0#
0%
b1100 !
#145000
b1101 !
#150000
1#
1%
b1110 !
#155000
b1111 !
#160000
0#
0$
0%
b10 "
b0 !
#165000
1%
b1 !
#170000
0%
b10 !
#175000
1%
b11 !
#180000
1#
1$
0%
b100 !
#185000
1%
b101 !
#190000
0%
b110 !
#195000
1%
b111 !
#200000
0#
0$
0%
b1000 !
#205000
1%
b1001 !
#210000
0%
b1010 !
#215000
1%
b1011 !
#220000
1#
1$
0%
b1100 !
#225000
1%
b1101 !
#230000
0%
b1110 !
#235000
1%
b1111 !
#240000
0#
0$
0%
b11 "
b0 !
#245000
b1 !
#250000
1%
b10 !
#255000
b11 !
#260000
0%
b100 !
#265000
b101 !
#270000
1%
b110 !
#275000
b111 !
#280000
1#
1$
0%
b1000 !
#285000
b1001 !
#290000
1%
b1010 !
#295000
b1011 !
#300000
0%
b1100 !
#305000
b1101 !
#310000
1%
b1110 !
#315000
b1111 !
