Q7/MUX2x1.v
`timescale 1ns / 1ps

module Mux2x1(in1, in2, s0, y);

    input in1, in2, s0;
    output y;
    wire Nots0, p, q;

    not N1(Nots0, s0);
    and A1(p, in1, Nots0);
    and A2(q, in2, s0);
    or O1(y, p, q);

endmodule

Q3/MUX/MUX4x1.v
`timescale 1ns / 1ps

module Mux4x1(in, s, y);

    input [3:0]in;
    input [1:0]s;
    output y;
    wire mux1, mux2;

    Mux2x1 Mux1(in[0], in[1], s[0], mux1);
    Mux2x1 Mux2(in[2], in[3], s[0], mux2);
    Mux2x1 Mux3(mux1, mux2, s[1], y);

endmodule

Q3/MUX/MUX8x1.v
`timescale 1ns / 1ps

module Mux8x1(in, s, y);

    input [7:0]in;
    input [2:0]s;
    output y, y2;
    wire mux1, mux2;

    Mux4x1 Mux1(in[3:0], s[1:0], mux1);
    Mux4x1 Mux2(in[7:4], s[1:0], mux2);
    // Mux2x1 Mux3(mux1, mux2, s[2], y);
    Mux4x1 Mux3({mux2, 1'b0, 1'b0, mux1}, {s[2], s[2]}, y2);

endmodule

Q3/MUX/MUX8x1_Testbench.v
`timescale 1ns / 1ps

module Mux8x1_Test;

    reg [7:0]in;
    reg [2:0]en;
    wire y;

    Mux8x1 uut(.in(in), .s(en), .y(y));

    initial begin
    
        $dumpfile("MUX8x1.vcd");
        $dumpvars(1, uut);

        // for(integer i = 0; i < 2048; i++)
        // begin
        //     {en[2], en[1], en[0], in[7], in[6], in[5], in[4], in[3], in[2], in[1], in[0]} = i; 
        //     #5;
        // end

        for(integer i = 0; i < 2048; i++)
        begin
            {en, in} = i; 
            #5;
        end

        $finish;

    end

endmodule

Q3/MUX/MUX8x1.vcd
$date
	Wed Oct  2 17:05:06 2024
$end
$version
	Icarus Verilog
$end
$timescale
	1ps
$end
$scope module Mux8x1_Test $end
$scope module uut $end
$var wire 8 ! in [7:0] $end
$var wire 3 " s [2:0] $end
$var wire 1 # y2 $end
$var wire 1 $ y $end
$var wire 1 % mux2 $end
$var wire 1 & mux1 $end
$upscope $end
$upscope $end
$enddefinitions $end
$comment Show the parameter values. $end
$dumpall
$end
#0
$dumpvars
0&
0%
0$
0#
b0 "
b0 !
$end
#5000
1#
1$
1&
b1 !
#10000
0#
0$
0&
b10 !
#15000
1#
1$
1&
b11 !
#20000
0#
0$
0&
b100 !
#25000
1#
1$
1&
b101 !
#30000
0#
0$
0&
b110 !
#35000
1#
1$
1&
b111 !
#40000
0#
0$
0&
b1000 !
#45000
1#
1$
1&
b1001 !
#50000
0#
0$
0&
b1010 !
#55000
1#
1$
1&
b1011 !
#60000
0#
0$
0&
b1100 !
#65000
1#
1$
1&
b1101 !
#70000
0#
0$
0&
b1110 !
#75000
1#
1$
1&
b1111 !
#80000
0#
0$
0&
1%
b10000 !
#85000
1#
1$
1&
b10001 !
#90000
0#
0$
0&
b10010 !
#95000
1#
1$
1&
b10011 !
#100000
0#
0$
0&
b10100 !
#105000
1#
1$
1&
b10101 !
#110000
0#
0$
0&
b10110 !
#115000
1#
1$
1&
b10111 !
#120000
0#
0$
0&
b11000 !
#125000
1#
1$
1&
b11001 !
#130000
0#
0$
0&
b11010 !
#135000
1#
1$
1&
b11011 !
#140000
0#
0$
0&
b11100 !
#145000
1#
1$
1&
b11101 !
#150000
0#
0$
0&
b11110 !
#155000
1#
1$
1&
b11111 !
#160000
0#
0$
0&
0%
b100000 !
#165000
1#
1$
1&
b100001 !
#170000
0#
0$
0&
b100010 !
#175000
1#
1$
1&
b100011 !
#180000
0#
0$
0&
b100100 !
#185000
1#
1$
1&
b100101 !
#190000
0#
0$
0&
b100110 !
#195000
1#
1$
1&
b100111 !
#200000
0#
0$
0&
b101000 !
#205000
1#
1$
1&
b101001 !
#210000
0#
0$
0&
b101010 !
#215000
1#
1$
1&
b101011 !
#220000
0#
0$
0&
b101100 !
#225000
1#
1$
1&
b101101 !
#230000
0#
0$
0&
b101110 !
#235000
1#
1$
1&
b101111 !
#240000
0#
0$
0&
1%
b110000 !
#245000
1#
1$
1&
b110001 !
#250000
0#
0$
0&
b110010 !
#255000
1#
1$
1&
b110011 !
#260000
0#
0$
0&
b110100 !
#265000
1#
1$
1&
b110101 !
#270000
0#
0$
0&
b110110 !
#275000
1#
1$
1&
b110111 !
#280000
0#
0$
0&
b111000 !
#285000
1#
1$
1&
b111001 !
#290000
0#
0$
0&
b111010 !
#295000
1#
1$
1&
b111011 !
#300000
0#
0$
0&
b111100 !
#305000
1#
1$
1&
b111101 !
#310000
0#
0$
0&
b111110 !
#315000
1#
1$
1&
b111111 !
#320000
0#
0$
0&
0%
b1000000 !
#325000
1#
1$
1&
b1000001 !
#330000
0#
0$
0&
b1000010 !
#335000
1#
1$
1&
b1000011 !
#340000
0#
0$
0&
b1000100 !
#345000
1#
1$
1&
b1000101 !
#350000
0#
0$
0&
b1000110 !
#355000
1#
1$
1&
b1000111 !
#360000
0#
0$
0&
b1001000 !
#365000
1#
1$
1&
b1001001 !
#370000
0#
0$
0&
b1001010 !
#375000
1#
1$
1&
b1001011 !
#380000
0#
0$
0&
b1001100 !
#385000
1#
1$
1&
b1001101 !
#390000
0#
0$
0&
b1001110 !
#395000
1#
1$
1&
b1001111 !
#400000
0#
0$
0&
1%
b1010000 !
#405000
1#
1$
1&
b1010001 !
#410000
0#
0$
0&
b1010010 !
#415000
1#
1$
1&
b1010011 !
#420000
0#
0$
0&
b1010100 !
#425000
1#
1$
1&
b1010101 !
#430000
0#
0$
0&
b1010110 !
#435000
1#
1$
1&
b1010111 !
#440000
0#
0$
0&
b1011000 !
#445000
1#
1$
1&
b1011001 !
#450000
0#
0$
0&
b1011010 !
#455000
1#
1$
1&
b1011011 !
#460000
0#
0$
0&
b1011100 !
#465000
1#
1$
1&
b1011101 !
#470000
0#
0$
0&
b1011110 !
#475000
1#
1$
1&
b1011111 !
#480000
0#
0$
0&
0%
b1100000 !
#485000
1#
1$
1&
b1100001 !
#490000
0#
0$
0&
b1100010 !
#495000
1#
1$
1&
b1100011 !
#500000
0#
0$
0&
b1100100 !
#505000
1#
1$
1&
b1100101 !
#510000
0#
0$
0&
b1100110 !
#515000
1#
1$
1&
b1100111 !
#520000
0#
0$
0&
b1101000 !
#525000
1#
1$
1&
b1101001 !
#530000
0#
0$
0&
b1101010 !
#535000
1#
1$
1&
b1101011 !
#540000
0#
0$
0&
b1101100 !
#545000
1#
1$
1&
b1101101 !
#550000
0#
0$
0&
b1101110 !
#555000
1#
1$
1&
b1101111 !
#560000
0#
0$
0&
1%
b1110000 !
#565000
1#
1$
1&
b1110001 !
#570000
0#
0$
0&
b1110010 !
#575000
1#
1$
1&
b1110011 !
#580000
0#
0$
0&
b1110100 !
#585000
1#
1$
1&
b1110101 !
#590000
0#
0$
0&
b1110110 !
#595000
1#
1$
1&
b1110111 !
#600000
0#
0$
0&
b1111000 !
#605000
1#
1$
1&
b1111001 !
#610000
0#
0$
0&
b1111010 !
#615000
1#
1$
1&
b1111011 !
#620000
0#
0$
0&
b1111100 !
#625000
1#
1$
1&
b1111101 !
#630000
0#
0$
0&
b1111110 !
#635000
1#
1$
1&
b1111111 !
#640000
0#
0$
0&
0%
b10000000 !
#645000
1#
1$
1&
b10000001 !
#650000
0#
0$
0&
b10000010 !
#655000
1#
1$
1&
b10000011 !
#660000
0#
0$
0&
b10000100 !
#665000
1#
1$
1&
b10000101 !
#670000
0#
0$
0&
b10000110 !
#675000
1#
1$
1&
b10000111 !
#680000
0#
0$
0&
b10001000 !
#685000
1#
1$
1&
b10001001 !
#690000
0#
0$
0&
b10001010 !
#695000
1#
1$
1&
b10001011 !
#700000
0#
0$
0&
b10001100 !
#705000
1#
1$
1&
b10001101 !
#710000
0#
0$
0&
b10001110 !
#715000
1#
1$
1&
b10001111 !
#720000
0#
0$
0&
1%
b10010000 !
#725000
1#
1$
1&
b10010001 !
#730000
0#
0$
0&
b10010010 !
#735000
1#
1$
1&
b10010011 !
#740000
0#
0$
0&
b10010100 !
#745000
1#
1$
1&
b10010101 !
#750000
0#
0$
0&
b10010110 !
#755000
1#
1$
1&
b10010111 !
#760000
0#
0$
0&
b10011000 !
#765000
1#
1$
1&
b10011001 !
#770000
0#
0$
0&
b10011010 !
#775000
1#
1$
1&
b10011011 !
#780000
0#
0$
0&
b10011100 !
#785000
1#
1$
1&
b10011101 !
#790000
0#
0$
0&
b10011110 !
#795000
1#
1$
1&
b10011111 !
#800000
0#
0$
0&
0%
b10100000 !
#805000
1#
1$
1&
b10100001 !
#810000
0#
0$
0&
b10100010 !
#815000
1#
1$
1&
b10100011 !
#820000
0#
0$
0&
b10100100 !
#825000
1#
1$
1&
b10100101 !
#830000
0#
0$
0&
b10100110 !
#835000
1#
1$
1&
b10100111 !
#840000
0#
0$
0&
b10101000 !
#845000
1#
1$
1&
b10101001 !
#850000
0#
0$
0&
b10101010 !
#855000
1#
1$
1&
b10101011 !
#860000
0#
0$
0&
b10101100 !
#865000
1#
1$
1&
b10101101 !
#870000
0#
0$
0&
b10101110 !
#875000
1#
1$
1&
b10101111 !
#880000
0#
0$
0&
1%
b10110000 !
#885000
1#
1$
1&
b10110001 !
#890000
0#
0$
0&
b10110010 !
#895000
1#
1$
1&
b10110011 !
#900000
0#
0$
0&
b10110100 !
#905000
1#
1$
1&
b10110101 !
#910000
0#
0$
0&
b10110110 !
#915000
1#
1$
1&
b10110111 !
#920000
0#
0$
0&
b10111000 !
#925000
1#
1$
1&
b10111001 !
#930000
0#
0$
0&
b10111010 !
#935000
1#
1$
1&
b10111011 !
#940000
0#
0$
0&
b10111100 !
#945000
1#
1$
1&
b10111101 !
#950000
0#
0$
0&
b10111110 !
#955000
1#
1$
1&
b10111111 !
#960000
0#
0$
0&
0%
b11000000 !
#965000
1#
1$
1&
b11000001 !
#970000
0#
0$
0&
b11000010 !
#975000
1#
1$
1&
b11000011 !
#980000
0#
0$
0&
b11000100 !
#985000
1#
1$
1&
b11000101 !
#990000
0#
0$
0&
b11000110 !
#995000
1#
1$
1&
b11000111 !
#1000000
0#
0$
0&
b11001000 !
#1005000
1#
1$
1&
b11001001 !
#1010000
0#
0$
0&
b11001010 !
#1015000
1#
1$
1&
b11001011 !
#1020000
0#
0$
0&
b11001100 !
#1025000
1#
1$
1&
b11001101 !
#1030000
0#
0$
0&
b11001110 !
#1035000
1#
1$
1&
b11001111 !
#1040000
0#
0$
0&
1%
b11010000 !
#1045000
1#
1$
1&
b11010001 !
#1050000
0#
0$
0&
b11010010 !
#1055000
1#
1$
1&
b11010011 !
#1060000
0#
0$
0&
b11010100 !
#1065000
1#
1$
1&
b11010101 !
#1070000
0#
0$
0&
b11010110 !
#1075000
1#
1$
1&
b11010111 !
#1080000
0#
0$
0&
b11011000 !
#1085000
1#
1$
1&
b11011001 !
#1090000
0#
0$
0&
b11011010 !
#1095000
1#
1$
1&
b11011011 !
#1100000
0#
0$
0&
b11011100 !
#1105000
1#
1$
1&
b11011101 !
#1110000
0#
0$
0&
b11011110 !
#1115000
1#
1$
1&
b11011111 !
#1120000
0#
0$
0&
0%
b11100000 !
#1125000
1#
1$
1&
b11100001 !
#1130000
0#
0$
0&
b11100010 !
#1135000
1#
1$
1&
b11100011 !
#1140000
0#
0$
0&
b11100100 !
#1145000
1#
1$
1&
b11100101 !
#1150000
0#
0$
0&
b11100110 !
#1155000
1#
1$
1&
b11100111 !
#1160000
0#
0$
0&
b11101000 !
#1165000
1#
1$
1&
b11101001 !
#1170000
0#
0$
0&
b11101010 !
#1175000
1#
1$
1&
b11101011 !
#1180000
0#
0$
0&
b11101100 !
#1185000
1#
1$
1&
b11101101 !
#1190000
0#
0$
0&
b11101110 !
#1195000
1#
1$
1&
b11101111 !
#1200000
0#
0$
0&
1%
b11110000 !
#1205000
1#
1$
1&
b11110001 !
#1210000
0#
0$
0&
b11110010 !
#1215000
1#
1$
1&
b11110011 !
#1220000
0#
0$
0&
b11110100 !
#1225000
1#
1$
1&
b11110101 !
#1230000
0#
0$
0&
b11110110 !
#1235000
1#
1$
1&
b11110111 !
#1240000
0#
0$
0&
b11111000 !
#1245000
1#
1$
1&
b11111001 !
#1250000
0#
0$
0&
b11111010 !
#1255000
1#
1$
1&
b11111011 !
#1260000
0#
0$
0&
b11111100 !
#1265000
1#
1$
1&
b11111101 !
#1270000
0#
0$
0&
b11111110 !
#1275000
1#
1$
1&
b11111111 !
#1280000
0#
0$
0&
0%
b1 "
b0 !
#1285000
b1 !
#1290000
1#
1$
1&
b10 !
#1295000
b11 !
#1300000
0#
0$
0&
b100 !
#1305000
b101 !
#1310000
1#
1$
1&
b110 !
#1315000
b111 !
#1320000
0#
0$
0&
b1000 !
#1325000
b1001 !
#1330000
1#
1$
1&
b1010 !
#1335000
b1011 !
#1340000
0#
0$
0&
b1100 !
#1345000
b1101 !
#1350000
1#
1$
1&
b1110 !
#1355000
b1111 !
#1360000
0#
0$
0&
b10000 !
#1365000
b10001 !
#1370000
1#
1$
1&
b10010 !
#1375000
b10011 !
#1380000
0#
0$
0&
b10100 !
#1385000
b10101 !
#1390000
1#
1$
1&
b10110 !
#1395000
b10111 !
#1400000
0#
0$
0&
b11000 !
#1405000
b11001 !
#1410000
1#
1$
1&
b11010 !
#1415000
b11011 !
#1420000
0#
0$
0&
b11100 !
#1425000
b11101 !
#1430000
1#
1$
1&
b11110 !
#1435000
b11111 !
#1440000
0#
0$
0&
1%
b100000 !
#1445000
b100001 !
#1450000
1#
1$
1&
b100010 !
#1455000
b100011 !
#1460000
0#
0$
0&
b100100 !
#1465000
b100101 !
#1470000
1#
1$
1&
b100110 !
#1475000
b100111 !
#1480000
0#
0$
0&
b101000 !
#1485000
b101001 !
#1490000
1#
1$
1&
b101010 !
#1495000
b101011 !
#1500000
0#
0$
0&
b101100 !
#1505000
b101101 !
#1510000
1#
1$
1&
b101110 !
#1515000
b101111 !
#1520000
0#
0$
0&
b110000 !
#1525000
b110001 !
#1530000
1#
1$
1&
b110010 !
#1535000
b110011 !
#1540000
0#
0$
0&
b110100 !
#1545000
b110101 !
#1550000
1#
1$
1&
b110110 !
#1555000
b110111 !
#1560000
0#
0$
0&
b111000 !
#1565000
b111001 !
#1570000
1#
1$
1&
b111010 !
#1575000
b111011 !
#1580000
0#
0$
0&
b111100 !
#1585000
b111101 !
#1590000
1#
1$
1&
b111110 !
#1595000
b111111 !
#1600000
0#
0$
0&
0%
b1000000 !
#1605000
b1000001 !
#1610000
1#
1$
1&
b1000010 !
#1615000
b1000011 !
#1620000
0#
0$
0&
b1000100 !
#1625000
b1000101 !
#1630000
1#
1$
1&
b1000110 !
#1635000
b1000111 !
#1640000
0#
0$
0&
b1001000 !
#1645000
b1001001 !
#1650000
1#
1$
1&
b1001010 !
#1655000
b1001011 !
#1660000
0#
0$
0&
b1001100 !
#1665000
b1001101 !
#1670000
1#
1$
1&
b1001110 !
#1675000
b1001111 !
#1680000
0#
0$
0&
b1010000 !
#1685000
b1010001 !
#1690000
1#
1$
1&
b1010010 !
#1695000
b1010011 !
#1700000
0#
0$
0&
b1010100 !
#1705000
b1010101 !
#1710000
1#
1$
1&
b1010110 !
#1715000
b1010111 !
#1720000
0#
0$
0&
b1011000 !
#1725000
b1011001 !
#1730000
1#
1$
1&
b1011010 !
#1735000
b1011011 !
#1740000
0#
0$
0&
b1011100 !
#1745000
b1011101 !
#1750000
1#
1$
1&
b1011110 !
#1755000
b1011111 !
#1760000
0#
0$
0&
1%
b1100000 !
#1765000
b1100001 !
#1770000
1#
1$
1&
b1100010 !
#1775000
b1100011 !
#1780000
0#
0$
0&
b1100100 !
#1785000
b1100101 !
#1790000
1#
1$
1&
b1100110 !
#1795000
b1100111 !
#1800000
0#
0$
0&
b1101000 !
#1805000
b1101001 !
#1810000
1#
1$
1&
b1101010 !
#1815000
b1101011 !
#1820000
0#
0$
0&
b1101100 !
#1825000
b1101101 !
#1830000
1#
1$
1&
b1101110 !
#1835000
b1101111 !
#1840000
0#
0$
0&
b1110000 !
#1845000
b1110001 !
#1850000
1#
1$
1&
b1110010 !
#1855000
b1110011 !
#1860000
0#
0$
0&
b1110100 !
#1865000
b1110101 !
#1870000
1#
1$
1&
b1110110 !
#1875000
b1110111 !
#1880000
0#
0$
0&
b1111000 !
#1885000
b1111001 !
#1890000
1#
1$
1&
b1111010 !
#1895000
b1111011 !
#1900000
0#
0$
0&
b1111100 !
#1905000
b1111101 !
#1910000
1#
1$
1&
b1111110 !
#1915000
b1111111 !
#1920000
0#
0$
0&
0%
b10000000 !
#1925000
b10000001 !
#1930000
1#
1$
1&
b10000010 !
#1935000
b10000011 !
#1940000
0#
0$
0&
b10000100 !
#1945000
b10000101 !
#1950000
1#
1$
1&
b10000110 !
#1955000
b10000111 !
#1960000
0#
0$
0&
b10001000 !
#1965000
b10001001 !
#1970000
1#
1$
1&
b10001010 !
#1975000
b10001011 !
#1980000
0#
0$
0&
b10001100 !
#1985000
b10001101 !
#1990000
1#
1$
1&
b10001110 !
#1995000
b10001111 !
#2000000
0#
0$
0&
b10010000 !
#2005000
b10010001 !
#2010000
1#
1$
1&
b10010010 !
#2015000
b10010011 !
#2020000
0#
0$
0&
b10010100 !
#2025000
b10010101 !
#2030000
1#
1$
1&
b10010110 !
#2035000
b10010111 !
#2040000
0#
0$
0&
b10011000 !
#2045000
b10011001 !
#2050000
1#
1$
1&
b10011010 !
#2055000
b10011011 !
#2060000
0#
0$
0&
b10011100 !
#2065000
b10011101 !
#2070000
1#
1$
1&
b10011110 !
#2075000
b10011111 !
#2080000
0#
0$
0&
1%
b10100000 !
#2085000
b10100001 !
#2090000
1#
1$
1&
b10100010 !
#2095000
b10100011 !
#2100000
0#
0$
0&
b10100100 !
#2105000
b10100101 !
#2110000
1#
1$
1&
b10100110 !
#2115000
b10100111 !
#2120000
0#
0$
0&
b10101000 !
#2125000
b10101001 !
#2130000
1#
1$
1&
b10101010 !
#2135000
b10101011 !
#2140000
0#
0$
0&
b10101100 !
#2145000
b10101101 !
#2150000
1#
1$
1&
b10101110 !
#2155000
b10101111 !
#2160000
0#
0$
0&
b10110000 !
#2165000
b10110001 !
#2170000
1#
1$
1&
b10110010 !
#2175000
b10110011 !
#2180000
0#
0$
0&
b10110100 !
#2185000
b10110101 !
#2190000
1#
1$
1&
b10110110 !
#2195000
b10110111 !
#2200000
0#
0$
0&
b10111000 !
#2205000
b10111001 !
#2210000
1#
1$
1&
b10111010 !
#2215000
b10111011 !
#2220000
0#
0$
0&
b10111100 !
#2225000
b10111101 !
#2230000
1#
1$
1&
b10111110 !
#2235000
b10111111 !
#2240000
0#
0$
0&
0%
b11000000 !
#2245000
b11000001 !
#2250000
1#
1$
1&
b11000010 !
#2255000
b11000011 !
#2260000
0#
0$
0&
b11000100 !
#2265000
b11000101 !
#2270000
1#
1$
1&
b11000110 !
#2275000
b11000111 !
#2280000
0#
0$
0&
b11001000 !
#2285000
b11001001 !
#2290000
1#
1$
1&
b11001010 !
#2295000
b11001011 !
#2300000
0#
0$
0&
b11001100 !
#2305000
b11001101 !
#2310000
1#
1$
1&
b11001110 !
#2315000
b11001111 !
#2320000
0#
0$
0&
b11010000 !
#2325000
b11010001 !
#2330000
1#
1$
1&
b11010010 !
#2335000
b11010011 !
#2340000
0#
0$
0&
b11010100 !
#2345000
b11010101 !
#2350000
1#
1$
1&
b11010110 !
#2355000
b11010111 !
#2360000
0#
0$
0&
b11011000 !
#2365000
b11011001 !
#2370000
1#
1$
1&
b11011010 !
#2375000
b11011011 !
#2380000
0#
0$
0&
b11011100 !
#2385000
b11011101 !
#2390000
1#
1$
1&
b11011110 !
#2395000
b11011111 !
#2400000
0#
0$
0&
1%
b11100000 !
#2405000
b11100001 !
#2410000
1#
1$
1&
b11100010 !
#2415000
b11100011 !
#2420000
0#
0$
0&
b11100100 !
#2425000
b11100101 !
#2430000
1#
1$
1&
b11100110 !
#2435000
b11100111 !
#2440000
0#
0$
0&
b11101000 !
#2445000
b11101001 !
#2450000
1#
1$
1&
b11101010 !
#2455000
b11101011 !
#2460000
0#
0$
0&
b11101100 !
#2465000
b11101101 !
#2470000
1#
1$
1&
b11101110 !
#2475000
b11101111 !
#2480000
0#
0$
0&
b11110000 !
#2485000
b11110001 !
#2490000
1#
1$
1&
b11110010 !
#2495000
b11110011 !
#2500000
0#
0$
0&
b11110100 !
#2505000
b11110101 !
#2510000
1#
1$
1&
b11110110 !
#2515000
b11110111 !
#2520000
0#
0$
0&
b11111000 !
#2525000
b11111001 !
#2530000
1#
1$
1&
b11111010 !
#2535000
b11111011 !
#2540000
0#
0$
0&
b11111100 !
#2545000
b11111101 !
#2550000
1#
1$
1&
b11111110 !
#2555000
b11111111 !
#2560000
0#
0$
0&
0%
b10 "
b0 !
#2565000
b1 !
#2570000
b10 !
#2575000
b11 !
#2580000
1#
1$
1&
b100 !
#2585000
b101 !
#2590000
b110 !
#2595000
b111 !
#2600000
0#
0$
0&
b1000 !
#2605000
b1001 !
#2610000
b1010 !
#2615000
b1011 !
#2620000
1#
1$
1&
b1100 !
#2625000
b1101 !
#2630000
b1110 !
#2635000
b1111 !
#2640000
0#
0$
0&
b10000 !
#2645000
b10001 !
#2650000
b10010 !
#2655000
b10011 !
#2660000
1#
1$
1&
b10100 !
#2665000
b10101 !
#2670000
b10110 !
#2675000
b10111 !
#2680000
0#
0$
0&
b11000 !
#2685000
b11001 !
#2690000
b11010 !
#2695000
b11011 !
#2700000
1#
1$
1&
b11100 !
#2705000
b11101 !
#2710000
b11110 !
#2715000
b11111 !
#2720000
0#
0$
0&
b100000 !
#2725000
b100001 !
#2730000
b100010 !
#2735000
b100011 !
#2740000
1#
1$
1&
b100100 !
#2745000
b100101 !
#2750000
b100110 !
#2755000
b100111 !
#2760000
0#
0$
0&
b101000 !
#2765000
b101001 !
#2770000
b101010 !
#2775000
b101011 !
#2780000
1#
1$
1&
b101100 !
#2785000
b101101 !
#2790000
b101110 !
#2795000
b101111 !
#2800000
0#
0$
0&
b110000 !
#2805000
b110001 !
#2810000
b110010 !
#2815000
b110011 !
#2820000
1#
1$
1&
b110100 !
#2825000
b110101 !
#2830000
b110110 !
#2835000
b110111 !
#2840000
0#
0$
0&
b111000 !
#2845000
b111001 !
#2850000
b111010 !
#2855000
b111011 !
#2860000
1#
1$
1&
b111100 !
#2865000
b111101 !
#2870000
b111110 !
#2875000
b111111 !
#2880000
0#
0$
0&
1%
b1000000 !
#2885000
b1000001 !
#2890000
b1000010 !
#2895000
b1000011 !
#2900000
1#
1$
1&
b1000100 !
#2905000
b1000101 !
#2910000
b1000110 !
#2915000
b1000111 !
#2920000
0#
0$
0&
b1001000 !
#2925000
b1001001 !
#2930000
b1001010 !
#2935000
b1001011 !
#2940000
1#
1$
1&
b1001100 !
#2945000
b1001101 !
#2950000
b1001110 !
#2955000
b1001111 !
#2960000
0#
0$
0&
b1010000 !
#2965000
b1010001 !
#2970000
b1010010 !
#2975000
b1010011 !
#2980000
1#
1$
1&
b1010100 !
#2985000
b1010101 !
#2990000
b1010110 !
#2995000
b1010111 !
#3000000
0#
0$
0&
b1011000 !
#3005000
b1011001 !
#3010000
b1011010 !
#3015000
b1011011 !
#3020000
1#
1$
1&
b1011100 !
#3025000
b1011101 !
#3030000
b1011110 !
#3035000
b1011111 !
#3040000
0#
0$
0&
b1100000 !
#3045000
b1100001 !
#3050000
b1100010 !
#3055000
b1100011 !
#3060000
1#
1$
1&
b1100100 !
#3065000
b1100101 !
#3070000
b1100110 !
#3075000
b1100111 !
#3080000
0#
0$
0&
b1101000 !
#3085000
b1101001 !
#3090000
b1101010 !
#3095000
b1101011 !
#3100000
1#
1$
1&
b1101100 !
#3105000
b1101101 !
#3110000
b1101110 !
#3115000
b1101111 !
#3120000
0#
0$
0&
b1110000 !
#3125000
b1110001 !
#3130000
b1110010 !
#3135000
b1110011 !
#3140000
1#
1$
1&
b1110100 !
#3145000
b1110101 !
#3150000
b1110110 !
#3155000
b1110111 !
#3160000
0#
0$
0&
b1111000 !
#3165000
b1111001 !
#3170000
b1111010 !
#3175000
b1111011 !
#3180000
1#
1$
1&
b1111100 !
#3185000
b1111101 !
#3190000
b1111110 !
#3195000
b1111111 !
#3200000
0#
0$
0&
0%
b10000000 !
#3205000
b10000001 !
#3210000
b10000010 !
#3215000
b10000011 !
#3220000
1#
1$
1&
b10000100 !
#3225000
b10000101 !
#3230000
b10000110 !
#3235000
b10000111 !
#3240000
0#
0$
0&
b10001000 !
#3245000
b10001001 !
#3250000
b10001010 !
#3255000
b10001011 !
#3260000
1#
1$
1&
b10001100 !
#3265000
b10001101 !
#3270000
b10001110 !
#3275000
b10001111 !
#3280000
0#
0$
0&
b10010000 !
#3285000
b10010001 !
#3290000
b10010010 !
#3295000
b10010011 !
#3300000
1#
1$
1&
b10010100 !
#3305000
b10010101 !
#3310000
b10010110 !
#3315000
b10010111 !
#3320000
0#
0$
0&
b10011000 !
#3325000
b10011001 !
#3330000
b10011010 !
#3335000
b10011011 !
#3340000
1#
1$
1&
b10011100 !
#3345000
b10011101 !
#3350000
b10011110 !
#3355000
b10011111 !
#3360000
0#
0$
0&
b10100000 !
#3365000
b10100001 !
#3370000
b10100010 !
#3375000
b10100011 !
#3380000
1#
1$
1&
b10100100 !
#3385000
b10100101 !
#3390000
b10100110 !
#3395000
b10100111 !
#3400000
0#
0$
0&
b10101000 !
#3405000
b10101001 !
#3410000
b10101010 !
#3415000
b10101011 !
#3420000
1#
1$
1&
b10101100 !
#3425000
b10101101 !
#3430000
b10101110 !
#3435000
b10101111 !
#3440000
0#
0$
0&
b10110000 !
#3445000
b10110001 !
#3450000
b10110010 !
#3455000
b10110011 !
#3460000
1#
1$
1&
b10110100 !
#3465000
b10110101 !
#3470000
b10110110 !
#3475000
b10110111 !
#3480000
0#
0$
0&
b10111000 !
#3485000
b10111001 !
#3490000
b10111010 !
#3495000
b10111011 !
#3500000
1#
1$
1&
b10111100 !
#3505000
b10111101 !
#3510000
b10111110 !
#3515000
b10111111 !
#3520000
0#
0$
0&
1%
b11000000 !
#3525000
b11000001 !
#3530000
b11000010 !
#3535000
b11000011 !
#3540000
1#
1$
1&
b11000100 !
#3545000
b11000101 !
#3550000
b11000110 !
#3555000
b11000111 !
#3560000
0#
0$
0&
b11001000 !
#3565000
b11001001 !
#3570000
b11001010 !
#3575000
b11001011 !
#3580000
1#
1$
1&
b11001100 !
#3585000
b11001101 !
#3590000
b11001110 !
#3595000
b11001111 !
#3600000
0#
0$
0&
b11010000 !
#3605000
b11010001 !
#3610000
b11010010 !
#3615000
b11010011 !
#3620000
1#
1$
1&
b11010100 !
#3625000
b11010101 !
#3630000
b11010110 !
#3635000
b11010111 !
#3640000
0#
0$
0&
b11011000 !
#3645000
b11011001 !
#3650000
b11011010 !
#3655000
b11011011 !
#3660000
1#
1$
1&
b11011100 !
#3665000
b11011101 !
#3670000
b11011110 !
#3675000
b11011111 !
#3680000
0#
0$
0&
b11100000 !
#3685000
b11100001 !
#3690000
b11100010 !
#3695000
b11100011 !
#3700000
1#
1$
1&
b11100100 !
#3705000
b11100101 !
#3710000
b11100110 !
#3715000
b11100111 !
#3720000
0#
0$
0&
b11101000 !
#3725000
b11101001 !
#3730000
b11101010 !
#3735000
b11101011 !
#3740000
1#
1$
1&
b11101100 !
#3745000
b11101101 !
#3750000
b11101110 !
#3755000
b11101111 !
#3760000
0#
0$
0&
b11110000 !
#3765000
b11110001 !
#3770000
b11110010 !
#3775000
b11110011 !
#3780000
1#
1$
1&
b11110100 !
#3785000
b11110101 !
#3790000
b11110110 !
#3795000
b11110111 !
#3800000
0#
0$
0&
b11111000 !
#3805000
b11111001 !
#3810000
b11111010 !
#3815000
b11111011 !
#3820000
1#
1$
1&
b11111100 !
#3825000
b11111101 !
#3830000
b11111110 !
#3835000
b11111111 !
#3840000
0#
0$
0&
0%
b11 "
b0 !
#3845000
b1 !
#3850000
b10 !
#3855000
b11 !
#3860000
b100 !
#3865000
b101 !
#3870000
b110 !
#3875000
b111 !
#3880000
1#
1$
1&
b1000 !
#3885000
b1001 !
#3890000
b1010 !
#3895000
b1011 !
#3900000
b1100 !
#3905000
b1101 !
#3910000
b1110 !
#3915000
b1111 !
#3920000
0#
0$
0&
b10000 !
#3925000
b10001 !
#3930000
b10010 !
#3935000
b10011 !
#3940000
b10100 !
#3945000
b10101 !
#3950000
b10110 !
#3955000
b10111 !
#3960000
1#
1$
1&
b11000 !
#3965000
b11001 !
#3970000
b11010 !
#3975000
b11011 !
#3980000
b11100 !
#3985000
b11101 !
#3990000
b11110 !
#3995000
b11111 !
#4000000
0#
0$
0&
b100000 !
#4005000
b100001 !
#4010000
b100010 !
#4015000
b100011 !
#4020000
b100100 !
#4025000
b100101 !
#4030000
b100110 !
#4035000
b100111 !
#4040000
1#
1$
1&
b101000 !
#4045000
b101001 !
#4050000
b101010 !
#4055000
b101011 !
#4060000
b101100 !
#4065000
b101101 !
#4070000
b101110 !
#4075000
b101111 !
#4080000
0#
0$
0&
b110000 !
#4085000
b110001 !
#4090000
b110010 !
#4095000
b110011 !
#4100000
b110100 !
#4105000
b110101 !
#4110000
b110110 !
#4115000
b110111 !
#4120000
1#
1$
1&
b111000 !
#4125000
b111001 !
#4130000
b111010 !
#4135000
b111011 !
#4140000
b111100 !
#4145000
b111101 !
#4150000
b111110 !
#4155000
b111111 !
#4160000
0#
0$
0&
b1000000 !
#4165000
b1000001 !
#4170000
b1000010 !
#4175000
b1000011 !
#4180000
b1000100 !
#4185000
b1000101 !
#4190000
b1000110 !
#4195000
b1000111 !
#4200000
1#
1$
1&
b1001000 !
#4205000
b1001001 !
#4210000
b1001010 !
#4215000
b1001011 !
#4220000
b1001100 !
#4225000
b1001101 !
#4230000
b1001110 !
#4235000
b1001111 !
