Q2/a/Logic_1.v
`timescale 1ns / 1ps

module Logic_1(a, b, c, d, y);

    input a, b, c, d;
    output y;
    wire p, q;

    // and A1(p, a, b);
    // and A2(q, c, d);
    // or O1(y, p, q);

    nand NA1(p, a, b);
    nand NA2(q, c, d);
    nand NA3(y, p, q);

    // assign y2 = (a & b) | (c & d);

endmodule

Q2/a/Logic_1_Testbench.v
`timescale 1ns / 1ps

module Logic_1_Test;

    reg a, b, c, d;
    wire y;

    Logic_1 uut(.a(a), .b(b), .c(c), .d(d), .y(y));

    initial begin
        $dumpfile("Logic_1.vcd");
        $dumpvars(1, uut);

        a = 1'b0;
        b = 1'b0;
        c = 1'b0;
        d = 1'b0;

        #100 $finish;
    end

    always #5 a = ~a;
    always #10 b = ~b;
    always #20 c = ~c;
    always #40 d = ~d;

endmodule

Q2/a/Logic_1.vcd
$date
	Sun Oct  6 10:12:27 2024
$end
$version
	Icarus Verilog
$end
$timescale
	1ps
$end
$scope module Logic_1_Test $end
$scope module uut $end
$var wire 1 ! a $end
$var wire 1 " b $end
$var wire 1 # c $end
$var wire 1 $ d $end
$var wire 1 % p $end
$var wire 1 & q $end
$var wire 1 ' y $end
$upscope $end
$upscope $end
$enddefinitions $end
$comment Show the parameter values. $end
$dumpall
$end
#0
$dumpvars
0'
1&
1%
0$
0#
0"
0!
$end
#5000
1!
#10000
0!
1"
#15000
1'
0%
1!
#20000
0'
1%
0!
0"
1#
#25000
1!
#30000
0!
1"
#35000
1'
0%
1!
#40000
0'
1%
0!
0"
0#
1$
#45000
1!
#50000
0!
1"
#55000
1'
0%
1!
#60000
1%
0&
0!
0"
1#
#65000
1!
#70000
0!
1"
#75000
0%
1!
#80000
0'
1%
1&
0!
0"
0#
0$
#85000
1!
#90000
0!
1"
#95000
1'
0%
1!
#100000
0'
1%
0!
0"
1#
