Q3/DEMUX/DEMUX1x2.v
`timescale 1ns / 1ps

module Demux1x2 (in, y, en);

    input in, en;
    output [1:0]y;
    wire en_not;

    not N1(en_not, en);
    and A1(y[0], en_not, in);
    and A2(y[1], en, in);
    
endmodule

Q3/DEMUX/DEMUX1x4.v
`timescale 1ns / 1ps

module Demux1x4 (in, y, en);

    input in;
    input [1:0]en;
    output [3:0]y;
    wire [1:0]Demux;

    Demux1x2 Demux1(.in(in), .en(en[1]), .y(Demux));
    Demux1x2 Demux2(.in(Demux[0]), .en(en[0]), .y(y[1:0]));
    Demux1x2 Demux3(.in(Demux[1]), .en(en[0]), .y(y[3:2]));
    
endmodule

Q3/DEMUX/DEMUX1x4_Testbench.v
`timescale 1ns / 1ps

module Demux1x4_Testbench;

    reg in;
    reg [1:0]en;
    wire [3:0]y;

    Demux1x4 uut(.in(in), .en(en), .y(y));

    initial begin

        $dumpfile("DEMUX1x4.vcd");
        $dumpvars(1, uut);

        in = 1'b0;
        en = 1'b0;

        for(integer i = 0; i < 8; i++)
        begin
            {en, in} = i;
            #5;
        end

        $finish;
    end
    
endmodule

Q3/DEMUX/DEMUX1x4.vcd
$date
	Wed Oct  2 15:33:31 2024
$end
$version
	Icarus Verilog
$end
$timescale
	1ps
$end
$scope module Demux1x4_Testbench $end
$scope module uut $end
$var wire 2 ! en [1:0] $end
$var wire 1 " in $end
$var wire 4 # y [3:0] $end
$var wire 2 $ Demux [1:0] $end
$upscope $end
$upscope $end
$enddefinitions $end
$comment Show the parameter values. $end
$dumpall
$end
#0
$dumpvars
b0 $
b0 #
0"
b0 !
$end
#5000
b1 #
b1 $
1"
#10000
b0 #
b0 $
b1 !
0"
#15000
b10 #
b1 $
1"
#20000
b0 #
b0 $
b10 !
0"
#25000
b100 #
b10 $
1"
#30000
b0 #
b0 $
b11 !
0"
#35000
b1000 #
b10 $
1"
