Q10/MooreFSM.v
// Output doesn't depend on input
`timescale 1ns / 1ps

module MooreFSM (input x, input Clk, input Clr, output reg y);

    reg [1:0]CurrState;
    reg [1:0]NextState;

    always @(posedge Clk or negedge Clr)
    begin
        if(!Clr)
        begin
            CurrState = 2'b00;
            NextState = ((x > 0) ? 2'b10 : 2'b01);
            y = 1'b0;
        end
        else
        begin
            CurrState = NextState;
            y = CurrState[0] ^ CurrState[1];
        end
    end

    always @(*)
    begin
        case(CurrState)
            2'b00 : NextState <= ((x > 0) ? 2'b10 : 2'b01);
            2'b01 : NextState <= ((x > 0) ? 2'b11 : 2'b10);
            2'b10 : NextState <= ((x > 0) ? 2'b11 : 2'b01);
            2'b11 : NextState <= ((x > 0) ? 2'b00 : 2'b10);
            default : NextState <= 2'b00;
        endcase
    end

endmodule

Q10/MooreFSM_Testbench.v
`timescale 1ns / 1ps

module MooreFSM_Testbench;

    reg Clk, Clr, x;
    wire y;

    MooreFSM uut(.Clk(Clk), .Clr(Clr), .x(x), .y(y));

    initial
    begin
        Clk = 0;
        Clr = 0;
        #1
        Clr = 1;
        forever #5 Clk = ~Clk; // 6, 16, 26, ...
    end

    initial
    begin
        $monitor("Time=%0t, x=%b, y=%b", $time, x, y);
    end

    initial
    begin
        $dumpfile("MooreFSM.vcd");
        $dumpvars(1, uut);
        
        x = 0;
        #30 // 0 -> 1 -> 2 -> 1
        x = 1;
        #40; // 1 -> 3 -> 0 -> 2 -> 3
        x = 0;
        #10 // 3 -> 2

        $finish;

    end

endmodule

Q10/MooreFSM.vcd
$date
	Sun Oct  6 19:57:49 2024
$end
$version
	Icarus Verilog
$end
$timescale
	1ps
$end
$scope module MooreFSM_Testbench $end
$scope module uut $end
$var wire 1 ! Clk $end
$var wire 1 " Clr $end
$var wire 1 # x $end
$var reg 2 $ CurrState [1:0] $end
$var reg 2 % NextState [1:0] $end
$var reg 1 & y $end
$upscope $end
$upscope $end
$enddefinitions $end
$comment Show the parameter values. $end
$dumpall
$end
#0
$dumpvars
0&
b1 %
b0 $
0#
0"
0!
$end
#1000
1"
#6000
b10 %
1&
b1 $
1!
#11000
0!
#16000
b1 %
b10 $
1!
#21000
0!
#26000
b10 %
b1 $
1!
#30000
b11 %
1#
#31000
0!
#36000
b0 %
0&
b11 $
1!
#41000
0!
#46000
b10 %
b0 $
1!
#51000
0!
#56000
b11 %
1&
b10 $
1!
#61000
0!
#66000
b0 %
0&
b11 $
1!
#70000
b10 %
0#
#71000
0!
#76000
b1 %
1&
b10 $
1!
