Q2/c/Logic_3.v
`timescale 1ns / 1ps

module Logic_3(a, b, c, d, e, y);

    input a, b, c, d, e;
    output y;
    wire p, q, r, s, t, u, v, y2; 

    // not N1(p, b);
    // or O1(q, a, p);

    // and A1(r, c, d);
    // or O2(s, e, r);

    // and(t, q, s);
    // not(y, t);

    nand NA1(p, a);
    nand NA2(q, c);
    nand NA3(r, d);
    nand NA4(s, e);
    nand NA5(t, p, b);
    nand NA6(u, q, s);
    nand NA7(v, r, s);
    nand NA8(y, t, u, v);

    // assign y2 = ~((a | ~b) & ((c & d) | e));

endmodule

Q2/c/Logic_3_Testbench.v
`timescale 1ns / 1ps

module Logic_3_Test;

    reg a, b, c, d, e;
    wire y;

    Logic_3 uut(.a(a), .b(b), .c(c), .d(d), .e(e), .y(y));

    initial begin
        $dumpfile("Logic_3.vcd");
        $dumpvars(1, uut);

        a = 1'b0;
        b = 1'b0;
        c = 1'b0;
        d = 1'b0;
        e = 1'b0;

        #160 $finish;
    end

    always #5 a = ~a;
    always #10 b = ~b;
    always #20 c = ~c;
    always #40 d = ~d;
    always #80 e = ~e;

endmodule

Q2/c/Logic_3.vcd
$date
	Sun Oct  6 09:59:12 2024
$end
$version
	Icarus Verilog
$end
$timescale
	1ps
$end
$scope module Logic_3_Test $end
$scope module uut $end
$var wire 1 ! a $end
$var wire 1 " b $end
$var wire 1 # c $end
$var wire 1 $ d $end
$var wire 1 % e $end
$var wire 1 & p $end
$var wire 1 ' q $end
$var wire 1 ( r $end
$var wire 1 ) s $end
$var wire 1 * t $end
$var wire 1 + u $end
$var wire 1 , v $end
$var wire 1 - y $end
$var wire 1 . y2 $end
$upscope $end
$upscope $end
$enddefinitions $end
$comment Show the parameter values. $end
$dumpall
$end
#0
$dumpvars
1.
1-
0,
0+
1*
1)
1(
1'
1&
0%
0$
0#
0"
0!
$end
#5000
0&
1!
#10000
0*
1&
0!
1"
#15000
1*
0&
1!
#20000
1+
1&
0'
0!
0"
1#
#25000
0&
1!
#30000
0*
1&
0!
1"
#35000
1*
0&
1!
#40000
0+
1,
1&
1'
0(
0!
0"
0#
1$
#45000
0&
1!
#50000
0*
1&
0!
1"
#55000
1*
0&
1!
#60000
0.
0-
1+
1&
0'
0!
0"
1#
#65000
0&
1!
#70000
1-
1.
0*
1&
0!
1"
#75000
0-
0.
1*
0&
1!
#80000
1&
1'
1(
0)
0!
0"
0#
0$
1%
#85000
0&
1!
#90000
1-
1.
0*
1&
0!
1"
#95000
0-
0.
1*
0&
1!
#100000
1&
0'
0!
0"
1#
#105000
0&
1!
#110000
1-
1.
0*
1&
0!
1"
#115000
0-
0.
1*
0&
1!
#120000
1&
1'
0(
0!
0"
0#
1$
#125000
0&
1!
#130000
1-
1.
0*
1&
0!
1"
#135000
0-
0.
1*
0&
1!
#140000
1&
0'
0!
0"
1#
#145000
0&
1!
#150000
1-
1.
0*
1&
0!
1"
#155000
0-
0.
1*
0&
1!
#160000
1.
1-
0+
0,
1&
1'
1(
1)
0!
0"
0#
0$
0%
