Q2/b/Logic_2.v
`timescale 1ns / 1ps

module Logic_2(a, b, c, d, e, f, y);

    input a, b, c, d, e, f;
    output y;
    wire p, q, r;

    // and A1(p, a, b, c);
    // and A2(q, d, e);
    // or O1(r, p, q);
    // and A3(y, r, f);

    nand NA1(p, a, b, c, f);
    nand NA2(q, d, e, f);
    nand NA3(y, p, q);

    // assign r = ((a & b & c) | (d & e)) & f;

endmodule

Q2/b/Logic_2_Testbench.v
`timescale 1ns / 1ps

module Logic_2_Test;

reg a, b, c, d, e, f;
wire y;

Logic_2 uut(.a(a), .b(b), .c(c), .d(d), .e(e), .f(f), .y(y));

initial begin
  $dumpfile("Logic_2.vcd");
  $dumpvars(1, uut);

  a = 1'b0;
  b = 1'b0;
  c = 1'b0;
  d = 1'b0;
  e = 1'b0;
  f = 1'b0;

  #320 $finish;
end

always #5 a = ~a;
always #10 b = ~b;
always #20 c = ~c;
always #40 d = ~d;
always #80 e = ~e;
always #160 f = ~f;

endmodule

Q2/b/Logic_2.vcd
$date
	Sun Oct  6 10:14:29 2024
$end
$version
	Icarus Verilog
$end
$timescale
	1ps
$end
$scope module Logic_2_Test $end
$scope module uut $end
$var wire 1 ! a $end
$var wire 1 " b $end
$var wire 1 # c $end
$var wire 1 $ d $end
$var wire 1 % e $end
$var wire 1 & f $end
$var wire 1 ' p $end
$var wire 1 ( q $end
$var wire 1 ) y $end
$upscope $end
$upscope $end
$enddefinitions $end
$comment Show the parameter values. $end
$dumpall
$end
#0
$dumpvars
0)
1(
1'
0&
0%
0$
0#
0"
0!
$end
#5000
1!
#10000
0!
1"
#15000
1!
#20000
0!
0"
1#
#25000
1!
#30000
0!
1"
#35000
1!
#40000
0!
0"
0#
1$
#45000
1!
#50000
0!
1"
#55000
1!
#60000
0!
0"
1#
#65000
1!
#70000
0!
1"
#75000
1!
#80000
0!
0"
0#
0$
1%
#85000
1!
#90000
0!
1"
#95000
1!
#100000
0!
0"
1#
#105000
1!
#110000
0!
1"
#115000
1!
#120000
0!
0"
0#
1$
#125000
1!
#130000
0!
1"
#135000
1!
#140000
0!
0"
1#
#145000
1!
#150000
0!
1"
#155000
1!
#160000
0!
0"
0#
0$
0%
1&
#165000
1!
#170000
0!
1"
#175000
1!
#180000
0!
0"
1#
#185000
1!
#190000
0!
1"
#195000
1)
0'
1!
#200000
0)
1'
0!
0"
0#
1$
#205000
1!
#210000
0!
1"
#215000
1!
#220000
0!
0"
1#
#225000
1!
#230000
0!
1"
#235000
1)
0'
1!
#240000
0)
1'
0!
0"
0#
0$
1%
#245000
1!
#250000
0!
1"
#255000
1!
#260000
0!
0"
1#
#265000
1!
#270000
0!
1"
#275000
1)
0'
1!
#280000
1'
0(
0!
0"
0#
1$
#285000
1!
#290000
0!
1"
#295000
1!
#300000
0!
0"
1#
#305000
1!
#310000
0!
1"
#315000
0'
1!
#320000
0)
1'
1(
0!
0"
0#
0$
0%
0&
