Q8/TFF.v
// Positive Edge Triggered Active Low Asynchronous Reset FLip FLip
`timescale 1ns / 1ps

module TFF(input T, input Clk, input Reset, output reg Q);
    
    always @(posedge Clk or negedge Reset) 
    begin
        if(!Reset)
            Q <= 1'b0;
        else
        begin
            if(T)
                Q = ~Q;
        end
    end

endmodule

Q8/RippleCounterNBit.v
`timescale 1ns / 1ps

`include "TFF.v"

module RippleCountNBit #(parameter N = 4)(input Cnt, input Clk, input Rst, output wire [N - 1 : 0]Count);

    genvar i;
    generate
        for(i = 0; i < N; i = i + 1)
        begin : Stage_Loop
        if(i == 0)
            TFF Tff(.T(1'b1), .Clk(Clk & Cnt), .Q(Count[i]), .Reset(Rst));    
        else
            TFF Tff(.T(1'b1), .Clk(~Count[i - 1]), .Q(Count[i]), .Reset(Rst));
        end
    endgenerate
    
endmodule

Q8/RippleCounter4Bit_Testbench.v
`timescale 1ns / 1ps

module RippleCount4Bit_Testbench;

    reg Cnt, Clk, Rst;
    wire [3 : 0]Out;

    RippleCountNBit #(.N(4)) uut(.Cnt(Cnt), .Clk(Clk), .Count(Out), .Rst(Rst));

    initial
    begin
        Clk = 0;
        #1;
        forever #5 Clk = ~Clk;
    end

    initial
    begin
        $dumpfile("RippleCount4Bit.vcd");
        $dumpvars(1, uut);    

        Rst = 0;
        Cnt = 0;
        #10;
        Cnt = 1;
        #10;
        Rst = 1;
        Cnt = 0;
        #10;
        Cnt = 1;
        #160;

        $finish;
    end

endmodule

Q8/RippleCount4Bit.vcd
$date
	Fri Oct  4 22:12:01 2024
$end
$version
	Icarus Verilog
$end
$timescale
	1ps
$end
$scope module RippleCount4Bit_Testbench $end
$scope module uut $end
$var wire 1 ! Clk $end
$var wire 1 " Cnt $end
$var wire 1 # Rst $end
$var wire 4 $ Count [3:0] $end
$var parameter 32 % N $end
$upscope $end
$upscope $end
$enddefinitions $end
$comment Show the parameter values. $end
$dumpall
b100 %
$end
#0
$dumpvars
bx $
0#
0"
0!
$end
#1000
b0 $
#6000
1!
#10000
1"
#11000
0!
#16000
1!
#20000
0"
1#
#21000
0!
#26000
1!
#30000
1"
#31000
b1 $
0!
#36000
1!
#37000
b0 $
#38000
b10 $
#41000
0!
#46000
1!
#47000
b11 $
#51000
0!
#56000
1!
#57000
b10 $
#58000
b0 $
#59000
b100 $
#61000
0!
#66000
1!
#67000
b101 $
#71000
0!
#76000
1!
#77000
b100 $
#78000
b110 $
#81000
0!
#86000
1!
#87000
b111 $
#91000
0!
#96000
1!
#97000
b110 $
#98000
b100 $
#99000
b0 $
#100000
b1000 $
#101000
0!
#106000
1!
#107000
b1001 $
#111000
0!
#116000
1!
#117000
b1000 $
#118000
b1010 $
#121000
0!
#126000
1!
#127000
b1011 $
#131000
0!
#136000
1!
#137000
b1010 $
#138000
b1000 $
#139000
b1100 $
#141000
0!
#146000
1!
#147000
b1101 $
#151000
0!
#156000
1!
#157000
b1100 $
#158000
b1110 $
#161000
0!
#166000
1!
#167000
b1111 $
#171000
0!
#176000
1!
#177000
b1110 $
#178000
b1100 $
#179000
b1000 $
#180000
b0 $
#181000
0!
#186000
1!
#187000
b1 $
