Q8/TFF.v
// Positive Edge Triggered Active Low Asynchronous Reset FLip FLip
`timescale 1ns / 1ps

module TFF(input T, input Clk, input Reset, output reg Q);
    
    always @(posedge Clk or negedge Reset) 
    begin
        if(!Reset)
            Q <= 1'b0;
        else
        begin
            if(T)
                Q = ~Q;
        end
    end

endmodule

Q8/UpDownBinCountNBit.v
`timescale 1ns / 1ps

`include "TFF.v"

// CntUp takes precedance in case both CntUp and CntDown are 1
module UpDownBinCountNBit #(parameter N = 4)(input CntUp, input CntDown, input Clk, input Rst, output wire [N - 1 : 0]Count);

    wire [N - 1 : 0]Up;
    wire [N - 1 : 0]Down;
    wire [N - 1 : 0]In;

    assign Up[0] = CntUp;
    assign Down[0] = (CntDown & (~CntUp));

    genvar i;
    generate
        for(i = 0; i < N; i = i + 1)
        begin : Stage_Loop
        if(i > 0)
        begin
            assign Up[i] = Up[i - 1] & Count[i - 1];
            assign Down[i] = Down[i - 1] & (~Count[i - 1]);
        end
        assign In[i] = Up[i] | Down[i];
        TFF Tff(.T(In[i]), .Clk(Clk), .Q(Count[i]), .Reset(Rst));
        end
    endgenerate
    
endmodule

Q8/UpDownBinCount4Bit_Testbench.v
`timescale 1ns / 1ps

module UpDownBinCount4Bit_Testbench;

    reg CntUp, CntDown, Clk, Rst;
    wire [3 : 0]Out;

    UpDownBinCountNBit #(.N(4)) uut(.CntUp(CntUp), .CntDown(CntDown), .Clk(Clk), .Count(Out), .Rst(Rst));

    initial
    begin
        Clk = 0;
        #1
        forever #5 Clk = ~Clk;
    end

    initial
    begin
        $dumpfile("UpDownBinCount4Bit.vcd");
        $dumpvars(1, uut);    

        Rst = 0;
        CntUp = 0;
        CntDown = 0;
        #5;
        CntUp = 1;
        CntDown = 0;
        #5;
        CntUp = 0;
        CntDown = 1;
        #5
        CntUp = 1;
        CntDown = 1;
        #5
        Rst = 1;
        CntUp = 0;
        CntDown = 0;
        #5;
        CntUp = 1;
        CntDown = 0;
        #200;
        CntDown = 1;
        #50;
        CntUp = 0;
        CntDown = 1;
        #200;

        $finish;
    end

endmodule

Q8/UpDownBinCount4Bit.vcd
$date
	Fri Oct  4 21:25:30 2024
$end
$version
	Icarus Verilog
$end
$timescale
	1ps
$end
$scope module UpDownBinCount4Bit_Testbench $end
$scope module uut $end
$var wire 1 ! Clk $end
$var wire 1 " CntDown $end
$var wire 1 # CntUp $end
$var wire 1 $ Rst $end
$var wire 4 % Up [3:0] $end
$var wire 4 & In [3:0] $end
$var wire 4 ' Down [3:0] $end
$var wire 4 ( Count [3:0] $end
$var parameter 32 ) N $end
$upscope $end
$upscope $end
$enddefinitions $end
$comment Show the parameter values. $end
$dumpall
b100 )
$end
#0
$dumpvars
b0 (
b0 '
b0 &
b0 %
0$
0#
0"
0!
$end
#5000
b1 &
b1 %
1#
#6000
1!
#10000
b1111 &
b1111 '
1"
b0 %
0#
#11000
0!
#15000
b1 &
b0 '
b1 %
1#
#16000
1!
#20000
b0 &
0"
b0 %
0#
1$
#21000
0!
#25000
b1 &
b1 %
1#
#26000
b11 &
b11 %
b1 (
1!
#31000
0!
#36000
b1 &
b1 %
b10 (
1!
#41000
0!
#46000
b111 &
b111 %
b11 (
1!
#51000
0!
#56000
b1 &
b1 %
b100 (
1!
#61000
0!
#66000
b11 &
b11 %
b101 (
1!
#71000
0!
#76000
b1 &
b1 %
b110 (
1!
#81000
0!
#86000
b1111 &
b1111 %
b111 (
1!
#91000
0!
#96000
b1 &
b1 %
b1000 (
1!
#101000
0!
#106000
b11 &
b11 %
b1001 (
1!
#111000
0!
#116000
b1 &
b1 %
b1010 (
1!
#121000
0!
#126000
b111 &
b111 %
b1011 (
1!
#131000
0!
#136000
b1 &
b1 %
b1100 (
1!
#141000
0!
#146000
b11 &
b11 %
b1101 (
1!
#151000
0!
#156000
b1 &
b1 %
b1110 (
1!
#161000
0!
#166000
b1111 &
b1111 %
b1111 (
1!
#171000
0!
#176000
b1 &
b1 %
b0 (
1!
#181000
0!
#186000
b11 &
b11 %
b1 (
1!
#191000
0!
#196000
b1 &
b1 %
b10 (
1!
#201000
0!
#206000
b111 &
b111 %
b11 (
1!
#211000
0!
#216000
b1 &
b1 %
b100 (
1!
#221000
0!
#225000
1"
#226000
b11 &
b11 %
b101 (
1!
#231000
0!
#236000
b1 &
b1 %
b110 (
1!
#241000
0!
#246000
b1111 &
b1111 %
b111 (
1!
#251000
0!
#256000
b1 &
b1 %
b1000 (
1!
#261000
0!
#266000
b11 &
b11 %
b1001 (
1!
#271000
0!
#275000
b1 &
b1 '
b0 %
0#
#276000
b1111 &
b1111 '
b1000 (
1!
#281000
0!
#286000
b1 &
b1 '
b111 (
1!
#291000
0!
#296000
b11 &
b11 '
b110 (
1!
#301000
0!
#306000
b1 &
b1 '
b101 (
1!
#311000
0!
#316000
b111 &
b111 '
b100 (
1!
#321000
0!
#326000
b1 &
b1 '
b11 (
1!
#331000
0!
#336000
b11 &
b11 '
b10 (
1!
#341000
0!
#346000
b1 &
b1 '
b1 (
1!
#351000
0!
#356000
b1111 &
b1111 '
b0 (
1!
#361000
0!
#366000
b1 &
b1 '
b1111 (
1!
#371000
0!
#376000
b11 &
b11 '
b1110 (
1!
#381000
0!
#386000
b1 &
b1 '
b1101 (
1!
#391000
0!
#396000
b111 &
b111 '
b1100 (
1!
#401000
0!
#406000
b1 &
b1 '
b1011 (
1!
#411000
0!
#416000
b11 &
b11 '
b1010 (
1!
#421000
0!
#426000
b1 &
b1 '
b1001 (
1!
#431000
0!
#436000
b1111 &
b1111 '
b1000 (
1!
#441000
0!
#446000
b1 &
b1 '
b111 (
1!
#451000
0!
#456000
b11 &
b11 '
b110 (
1!
#461000
0!
#466000
b1 &
b1 '
b101 (
1!
