Q3/DECODER/DECODER1x2.v
`timescale 1ns / 1ps

module Decoder1x2 (en, in, out);

    input en;
    input in;
    output [1:0]out;
    wire in_not;

    not N1(in_not, in);
    and A1(out[0], en, in_not);
    and A2(out[1], en, in);
    
endmodule

Q3/DECODER/DECODER2x4.v
`timescale 1ns / 1ps

module Decoder2x4 (en, in, out);

    input en;
    input [1:0]in; // in[0] = A, ...
    output [3:0]out; // out[0] = A'B', ... 
    wire [1:0]DecodedInA; // DecodedInA[0] = A', ...

    Decoder1x2 Decoder1(.in(in[0]), .en(en), .out(DecodedInA));
    Decoder1x2 Decoder2(.in(in[1]), .en(DecodedInA[0]), .out(out[1:0]));
    Decoder1x2 Decoder3(.in(in[1]), .en(DecodedInA[1]), .out(out[3:2]));

endmodule

Q3/DECODER/DECODER3x8.v
`timescale 1ns / 1ps

module Decoder3x8 (en, in, out);

    input en;
    input [2:0]in; // in[0] = A, ...
    output [7:0]out; // out[0] = A'B'C', ... 
    // wire [1:0]DecodedInA; // DecodedInA[0] = A', ...
    wire [3:0]DecodedInA;

    // Decoder1x2 Decoder1(.in(in[0]), .en(en), .out(DecodedInA));
    Decoder2x4 Decoder1(.in({in[0], in[0]}), .en(en), .out(DecodedInA));
    Decoder2x4 Decoder2(.in(in[2:1]), .en(DecodedInA[0]), .out(out[3:0]));
    // Decoder2x4 Decoder3(.in(in[2:1]), .en(DecodedInA[1]), .out(out[7:4]));
    Decoder2x4 Decoder3(.in(in[2:1]), .en(DecodedInA[3]), .out(out[7:4]));

endmodule

Q3/DECODER/DECODER3x8_Testbench.v
`timescale 1ns / 1ps

module Decoder2x4_Testbench;

    reg [2:0]in;
    reg en;
    wire [7:0]out;

    Decoder3x8 uut(.en(en), .in(in), .out(out));

    initial
    begin
        
        $dumpfile("DECODER3x8.vcd");
        $dumpvars(1, uut);

        in = 1'b0;
        en = 1'b0;

        for(integer i = 0; i < 16; i++)
        begin
            {en, in} = i; // Order of change here is DBCA (0000->0001)
            #5;
        end

        $finish;

    end

endmodule

Q3/DECODER/DECODER3x8.vcd
$date
	Wed Oct  2 17:21:01 2024
$end
$version
	Icarus Verilog
$end
$timescale
	1ps
$end
$scope module Decoder2x4_Testbench $end
$scope module uut $end
$var wire 1 ! en $end
$var wire 3 " in [2:0] $end
$var wire 8 # out [7:0] $end
$var wire 4 $ DecodedInA [3:0] $end
$upscope $end
$upscope $end
$enddefinitions $end
$comment Show the parameter values. $end
$dumpall
$end
#0
$dumpvars
b0 $
b0 #
b0 "
0!
$end
#5000
b1 "
#10000
b10 "
#15000
b11 "
#20000
b100 "
#25000
b101 "
#30000
b110 "
#35000
b111 "
#40000
b1 #
b1 $
1!
b0 "
#45000
b10000 #
b1000 $
b1 "
#50000
b100 #
b1 $
b10 "
#55000
b1000000 #
b1000 $
b11 "
#60000
b1 $
b10 #
b100 "
#65000
b100000 #
b1000 $
b101 "
#70000
b1000 #
b1 $
b110 "
#75000
b10000000 #
b1000 $
b111 "
