Q3/DECODER/DECODER1x2.v
`timescale 1ns / 1ps

module Decoder1x2 (en, in, out);

    input en;
    input in;
    output [1:0]out;
    wire in_not;

    not N1(in_not, in);
    and A1(out[0], en, in_not);
    and A2(out[1], en, in);
    
endmodule

Q3/DECODER/DECODER2x4.v
`timescale 1ns / 1ps

module Decoder2x4 (en, in, out);

    input en;
    input [1:0]in; // in[0] = A, ...
    output [3:0]out; // out[0] = A'B', ... 
    wire [1:0]DecodedInA; // DecodedInA[0] = A', ...

    Decoder1x2 Decoder1(.in(in[0]), .en(en), .out(DecodedInA));
    Decoder1x2 Decoder2(.in(in[1]), .en(DecodedInA[0]), .out(out[1:0]));
    Decoder1x2 Decoder3(.in(in[1]), .en(DecodedInA[1]), .out(out[3:2]));

endmodule

Q3/DECODER/DECODER2x4_Testbench.v
`timescale 1ns / 1ps

module Decoder2x4_Testbench;

    reg [1:0]in;
    reg en;
    wire [3:0]out;

    Decoder2x4 uut(.en(en), .in(in), .out(out));

    initial
    begin
        
        $dumpfile("DECODER2x4.vcd");
        $dumpvars(1, uut);

        in = 1'b0;
        en = 1'b0;

        for(integer i = 0; i < 8; i++)
        begin
            {en, in} = i; // Order of change here is DBCA (0000->0001)
            #5;
        end

        $finish;

    end

endmodule

Q3/DECODER/DECODER2x4.vcd
$date
	Wed Oct  2 16:10:57 2024
$end
$version
	Icarus Verilog
$end
$timescale
	1ps
$end
$scope module Decoder2x4_Testbench $end
$scope module uut $end
$var wire 1 ! en $end
$var wire 2 " in [1:0] $end
$var wire 4 # out [3:0] $end
$var wire 2 $ DecodedInA [1:0] $end
$upscope $end
$upscope $end
$enddefinitions $end
$comment Show the parameter values. $end
$dumpall
$end
#0
$dumpvars
b0 $
b0 #
b0 "
0!
$end
#5000
b1 "
#10000
b10 "
#15000
b11 "
#20000
b1 #
b1 $
1!
b0 "
#25000
b100 #
b10 $
b1 "
#30000
b1 $
b10 #
b10 "
#35000
b1000 #
b10 $
b11 "
